LICENSE.md
README.rst
pyproject.toml
setup.cfg
setup.py
/Users/julianporter/git/FLPFiles/src/parse_flp
src/FLP/__init__.py
src/FLP/base.py
src/FLP/partitioner.py
src/FLP/chunks/__init__.py
src/FLP/chunks/chunk.py
src/FLP/chunks/event.py
src/FLP/chunks/header.py
src/FLP/chunks/track.py
src/FLP/messagetypes/__init__.py
src/FLP/messagetypes/core.py
src/FLP/messagetypes/int16messages.py
src/FLP/messagetypes/int32messages.py
src/FLP/messagetypes/int8messages.py
src/FLP/messagetypes/textmessages.py
src/FLP/messagetypes/text/__init__.py
src/FLP/messagetypes/text/base.py
src/FLP/messagetypes/text/defs.py
src/FLP/messagetypes/text/numeric.py
src/FLP/messagetypes/text/text.py
src/FLPFile.egg-info/PKG-INFO
src/FLPFile.egg-info/SOURCES.txt
src/FLPFile.egg-info/dependency_links.txt
src/FLPFile.egg-info/top_level.txt