Metadata-Version: 2.1
Name: FLPFile
Version: 0.2.0
Summary: A simple FL Studio Project File parser
Home-page: https://github.com/jdstmporter/FLPFiles.git
Author: Julian Porter
Author-email: julian@porternet.org
License: UNKNOWN
Keywords: FL Studio Project File,FLP file
Platform: UNKNOWN
Classifier: Development Status :: 4 - Beta
Classifier: Environment :: Console
Classifier: Intended Audience :: Developers
Classifier: Intended Audience :: Other Audience
Classifier: License :: OSI Approved :: MIT License
Classifier: Natural Language :: English
Classifier: Operating System :: MacOS
Classifier: Operating System :: POSIX :: Linux
Classifier: Programming Language :: Python :: 3
Classifier: Programming Language :: Python :: 3.6
Classifier: Programming Language :: Python :: 3.7
Classifier: Programming Language :: Python :: 3.8
Classifier: Programming Language :: Python :: 3.9
Requires-Python: >=3.6, <4
